{"is_source_file": false, "format": "", "description": "", "external_files": [], "external_methods": [], "published": [], "classes": [], "methods": [], "calls": [], "search-terms": [], "state": 2, "file_id": 1, "knowledge_revision": 21, "git_revision": "2c91157e2b7c3638dffed626fc62236ac12d9d59", "hash": "16bc3bf6215759390e75e4089fa1a713", "format-version": 4, "code-base-name": "tic_tac_toe_frontend", "filename": "README.md", "revision_history": [{"21": "2c91157e2b7c3638dffed626fc62236ac12d9d59"}]}